levseq/IO_processor.py
levseq/__init__.py
levseq/basecaller.py
levseq/cmd.py
levseq/coordinates.py
levseq/filter_orientation.py
levseq/globals.py
levseq/interface.py
levseq/parser.py
levseq/run_levseq.py
levseq/screen.py
levseq/seqfit.py
levseq/simulation.py
levseq/user.py
levseq/utils.py
levseq/variantcaller.py
levseq/visualization.py
levseq/barcoding/__init__.py
levseq/barcoding/demultiplex
levseq/barcoding/demultiplex-arm64
levseq/barcoding/demultiplex-x86
levseq/barcoding/minion_barcodes.fasta
levseq-1.5.data/data/LICENSE
levseq-1.5.dist-info/licenses/LICENSE
levseq-1.5.dist-info/METADATA
levseq-1.5.dist-info/WHEEL
levseq-1.5.dist-info/entry_points.txt
levseq-1.5.dist-info/top_level.txt
levseq-1.5.dist-info/RECORD
