Metadata-Version: 2.4
Name: levseq
Version: 1.5
Home-page: https://github.com/fhalab/levseq/
Author: Yueming Long, Ariane Mora, Francesca-Zhoufan Li, Emre Gursoy
Author-email: ylong@caltech.edu
License: GPL3
Project-URL: Bug Tracker, https://github.com/fhalab/levseq/
Project-URL: Documentation, https://github.com/fhalab/levseq/
Project-URL: Source Code, https://github.com/fhalab/levseq/
Keywords: Nanopore,ONT,evSeq
Classifier: Development Status :: 5 - Production/Stable
Classifier: Intended Audience :: Science/Research
Classifier: License :: OSI Approved :: GNU General Public License v3 (GPLv3)
Classifier: Natural Language :: English
Classifier: Operating System :: OS Independent
Classifier: Programming Language :: Python :: 3.6
Classifier: Programming Language :: Python :: 3.7
Classifier: Programming Language :: Python :: 3.8
Classifier: Topic :: Scientific/Engineering :: Bio-Informatics
Requires-Python: >=3.8
License-File: LICENSE
Requires-Dist: Bio
Requires-Dist: biopython
Requires-Dist: fsspec
Requires-Dist: h5py
Requires-Dist: holoviews
Requires-Dist: jupyterlab
Requires-Dist: mappy
Requires-Dist: matplotlib
Requires-Dist: ninetysix
Requires-Dist: numpy
Requires-Dist: pandas
Requires-Dist: pybedtools
Requires-Dist: pycoQC
Requires-Dist: pyfaidx
Requires-Dist: pyparsing
Requires-Dist: pysam
Requires-Dist: scipy
Requires-Dist: sciutil
Requires-Dist: seaborn
Requires-Dist: scikit-learn
Requires-Dist: statsmodels
Requires-Dist: tqdm
Requires-Dist: biopandas
Dynamic: author
Dynamic: author-email
Dynamic: classifier
Dynamic: description
Dynamic: description-content-type
Dynamic: home-page
Dynamic: keywords
Dynamic: license
Dynamic: license-file
Dynamic: project-url
Dynamic: requires-dist
Dynamic: requires-python
